[
	{
		"abbreviation": {
			"en_US": "N/A",
			"es_AR": "ALIANZA + VALORES"
		},
		"area_id": 2,
		"coalition_id": "",
		"colors": [
			""
		],
		"fb_urls": [],
		"id": 1,
		"ig_urls": [],
		"logo_urls": [],
		"name": {
			"en_US": "ALIANZA + VALORES",
			"es_AR": "ALIANZA + VALORES"
		},
		"websites": []
	},
	{
		"abbreviation": {
			"en_US": "N/A",
			"es_AR": "ALIANZA AVANZA LA LIBERTAD"
		},
		"area_id": 6,
		"coalition_id": 5,
		"colors": [
			""
		],
		"fb_urls": [],
		"id": 2,
		"ig_urls": [],
		"logo_urls": [],
		"name": {
			"en_US": "ALIANZA AVANZA LA LIBERTAD",
			"es_AR": "ALIANZA AVANZA LA LIBERTAD"
		},
		"websites": []
	},
	{
		"abbreviation": {
			"en_US": "N/A",
			"es_AR": "ALIANZA AVANZA LIBERTAD"
		},
		"area_id": 2,
		"coalition_id": 5,
		"colors": [
			""
		],
		"fb_urls": [],
		"id": 3,
		"ig_urls": [],
		"logo_urls": [],
		"name": {
			"en_US": "ALIANZA AVANZA LIBERTAD",
			"es_AR": "ALIANZA AVANZA LIBERTAD"
		},
		"websites": []
	},
	{
		"abbreviation": {
			"en_US": "N/A",
			"es_AR": "ALIANZA CHACO CAMBIA + JUNTOS POR EL CAMBIO"
		},
		"area_id": 4,
		"coalition_id": 2,
		"colors": [
			""
		],
		"fb_urls": [],
		"id": 4,
		"ig_urls": [],
		"logo_urls": [],
		"name": {
			"en_US": "ALIANZA CHACO CAMBIA + JUNTOS POR EL CAMBIO",
			"es_AR": "ALIANZA CHACO CAMBIA + JUNTOS POR EL CAMBIO"
		},
		"websites": []
	},
	{
		"abbreviation": {
			"en_US": "N/A",
			"es_AR": "ALIANZA FITU SAN LUIS"
		},
		"area_id": 20,
		"coalition_id": 3,
		"colors": [
			""
		],
		"fb_urls": [],
		"id": 5,
		"ig_urls": [],
		"logo_urls": [],
		"name": {
			"en_US": "ALIANZA FITU SAN LUIS",
			"es_AR": "ALIANZA FITU SAN LUIS"
		},
		"websites": []
	},
	{
		"abbreviation": {
			"en_US": "N/A",
			"es_AR": "ALIANZA FRENTE DE TODOS"
		},
		"area_id": 1,
		"coalition_id": 1,
		"colors": [
			""
		],
		"fb_urls": [],
		"id": 6,
		"ig_urls": [],
		"logo_urls": [],
		"name": {
			"en_US": "ALIANZA FRENTE DE TODOS",
			"es_AR": "ALIANZA FRENTE DE TODOS"
		},
		"websites": []
	},
	{
		"abbreviation": {
			"en_US": "N/A",
			"es_AR": "ALIANZA FRENTE VAMOS CON VOS"
		},
		"area_id": 1,
		"coalition_id": 4,
		"colors": [
			""
		],
		"fb_urls": [],
		"id": 7,
		"ig_urls": [],
		"logo_urls": [],
		"name": {
			"en_US": "ALIANZA FRENTE VAMOS CON VOS",
			"es_AR": "ALIANZA FRENTE VAMOS CON VOS"
		},
		"websites": []
	},
	{
		"abbreviation": {
			"en_US": "N/A",
			"es_AR": "ALIANZA FUERZA SAN LUIS"
		},
		"area_id": 20,
		"coalition_id": 6,
		"colors": [
			""
		],
		"fb_urls": [],
		"id": 8,
		"ig_urls": [],
		"logo_urls": [],
		"name": {
			"en_US": "ALIANZA FUERZA SAN LUIS",
			"es_AR": "ALIANZA FUERZA SAN LUIS"
		},
		"websites": []
	},
	{
		"abbreviation": {
			"en_US": "N/A",
			"es_AR": "ALIANZA JUNTOS"
		},
		"area_id": 2,
		"coalition_id": 2,
		"colors": [
			""
		],
		"fb_urls": [],
		"id": 9,
		"ig_urls": [],
		"logo_urls": [],
		"name": {
			"en_US": "ALIANZA JUNTOS",
			"es_AR": "ALIANZA JUNTOS"
		},
		"websites": []
	},
	{
		"abbreviation": {
			"en_US": "N/A",
			"es_AR": "ALIANZA UNIDOS POR SAN LUIS"
		},
		"area_id": 20,
		"coalition_id": 6,
		"colors": [
			""
		],
		"fb_urls": [],
		"id": 10,
		"ig_urls": [],
		"logo_urls": [],
		"name": {
			"en_US": "ALIANZA UNIDOS POR SAN LUIS",
			"es_AR": "ALIANZA UNIDOS POR SAN LUIS"
		},
		"websites": []
	},
	{
		"abbreviation": {
			"en_US": "N/A",
			"es_AR": "ALIANZA VAMOS CON VOS"
		},
		"area_id": 8,
		"coalition_id": 4,
		"colors": [
			""
		],
		"fb_urls": [],
		"id": 11,
		"ig_urls": [],
		"logo_urls": [],
		"name": {
			"en_US": "ALIANZA VAMOS CON VOS",
			"es_AR": "ALIANZA VAMOS CON VOS"
		},
		"websites": []
	},
	{
		"abbreviation": {
			"en_US": "N/A",
			"es_AR": "AUTODETERMINACIÓN Y LIBERTAD"
		},
		"area_id": 6,
		"coalition_id": 3,
		"colors": [
			""
		],
		"fb_urls": [],
		"id": 12,
		"ig_urls": [],
		"logo_urls": [],
		"name": {
			"en_US": "AUTODETERMINACIÓN Y LIBERTAD",
			"es_AR": "AUTODETERMINACIÓN Y LIBERTAD"
		},
		"websites": []
	},
	{
		"abbreviation": {
			"en_US": "N/A",
			"es_AR": "CAMBIA JUJUY"
		},
		"area_id": 11,
		"coalition_id": 2,
		"colors": [
			""
		],
		"fb_urls": [],
		"id": 13,
		"ig_urls": [],
		"logo_urls": [],
		"name": {
			"en_US": "CAMBIA JUJUY",
			"es_AR": "CAMBIA JUJUY"
		},
		"websites": []
	},
	{
		"abbreviation": {
			"en_US": "N/A",
			"es_AR": "CAMBIA MENDOZA - DISTRITO MENDOZA"
		},
		"area_id": 14,
		"coalition_id": 2,
		"colors": [
			""
		],
		"fb_urls": [],
		"id": 14,
		"ig_urls": [],
		"logo_urls": [],
		"name": {
			"en_US": "CAMBIA MENDOZA - DISTRITO MENDOZA",
			"es_AR": "CAMBIA MENDOZA - DISTRITO MENDOZA"
		},
		"websites": []
	},
	{
		"abbreviation": {
			"en_US": "N/A",
			"es_AR": "CAMBIA NEUQUÉN"
		},
		"area_id": 16,
		"coalition_id": 2,
		"colors": [
			""
		],
		"fb_urls": [],
		"id": 15,
		"ig_urls": [],
		"logo_urls": [],
		"name": {
			"en_US": "CAMBIA NEUQUÉN",
			"es_AR": "CAMBIA NEUQUÉN"
		},
		"websites": []
	},
	{
		"abbreviation": {
			"en_US": "N/A",
			"es_AR": "CAMBIA SANTA CRUZ"
		},
		"area_id": 21,
		"coalition_id": 2,
		"colors": [
			""
		],
		"fb_urls": [],
		"id": 16,
		"ig_urls": [],
		"logo_urls": [],
		"name": {
			"en_US": "CAMBIA SANTA CRUZ",
			"es_AR": "CAMBIA SANTA CRUZ"
		},
		"websites": []
	},
	{
		"abbreviation": {
			"en_US": "N/A",
			"es_AR": "CHUBUT SOMOS TODOS"
		},
		"area_id": 5,
		"coalition_id": 1,
		"colors": [
			""
		],
		"fb_urls": [],
		"id": 17,
		"ig_urls": [],
		"logo_urls": [],
		"name": {
			"en_US": "CHUBUT SOMOS TODOS",
			"es_AR": "CHUBUT SOMOS TODOS"
		},
		"websites": []
	},
	{
		"abbreviation": {
			"en_US": "CC-ARI",
			"es_AR": "COALICION CIVICA - ARI"
		},
		"area_id": 16,
		"coalition_id": 2,
		"colors": [
			""
		],
		"fb_urls": [],
		"id": 18,
		"ig_urls": [],
		"logo_urls": [],
		"name": {
			"en_US": "COALICION CIVICA - ARI",
			"es_AR": "COALICION CIVICA - ARI"
		},
		"websites": []
	},
	{
		"abbreviation": {
			"en_US": "N/A",
			"es_AR": "COMPROMISO FEDERAL"
		},
		"area_id": 8,
		"coalition_id": 1,
		"colors": [
			""
		],
		"fb_urls": [],
		"id": 19,
		"ig_urls": [],
		"logo_urls": [],
		"name": {
			"en_US": "COMPROMISO FEDERAL",
			"es_AR": "COMPROMISO FEDERAL"
		},
		"websites": []
	},
	{
		"abbreviation": {
			"en_US": "N/A",
			"es_AR": "COMPROMISO FEDERAL - DISTRITO MENDOZA"
		},
		"area_id": 14,
		"coalition_id": 1,
		"colors": [
			""
		],
		"fb_urls": [],
		"id": 20,
		"ig_urls": [],
		"logo_urls": [],
		"name": {
			"en_US": "COMPROMISO FEDERAL - DISTRITO MENDOZA",
			"es_AR": "COMPROMISO FEDERAL - DISTRITO MENDOZA"
		},
		"websites": []
	},
	{
		"abbreviation": {
			"en_US": "N/A",
			"es_AR": "CORRIENTE DE PENSAMIENTO BONAERENSE"
		},
		"area_id": 3,
		"coalition_id": 6,
		"colors": [
			""
		],
		"fb_urls": [],
		"id": 21,
		"ig_urls": [],
		"logo_urls": [],
		"name": {
			"en_US": "CORRIENTE DE PENSAMIENTO BONAERENSE",
			"es_AR": "CORRIENTE DE PENSAMIENTO BONAERENSE"
		},
		"websites": []
	},
	{
		"abbreviation": {
			"en_US": "N/A",
			"es_AR": "DEL OBRERO"
		},
		"area_id": 15,
		"coalition_id": 3,
		"colors": [
			""
		],
		"fb_urls": [],
		"id": 22,
		"ig_urls": [],
		"logo_urls": [],
		"name": {
			"en_US": "DEL OBRERO",
			"es_AR": "DEL OBRERO"
		},
		"websites": []
	},
	{
		"abbreviation": {
			"en_US": "N/A",
			"es_AR": "ECO + VAMOS CORRIENTES"
		},
		"area_id": 8,
		"coalition_id": 2,
		"colors": [
			""
		],
		"fb_urls": [],
		"id": 23,
		"ig_urls": [],
		"logo_urls": [],
		"name": {
			"en_US": "ECO + VAMOS CORRIENTES",
			"es_AR": "ECO + VAMOS CORRIENTES"
		},
		"websites": []
	},
	{
		"abbreviation": {
			"en_US": "N/A",
			"es_AR": "ENCUENTRO VECINAL CORDOBA"
		},
		"area_id": 7,
		"coalition_id": 6,
		"colors": [
			""
		],
		"fb_urls": [],
		"id": 24,
		"ig_urls": [],
		"logo_urls": [],
		"name": {
			"en_US": "ENCUENTRO VECINAL CORDOBA",
			"es_AR": "ENCUENTRO VECINAL CORDOBA"
		},
		"websites": []
	},
	{
		"abbreviation": {
			"en_US": "N/A",
			"es_AR": "FELICIDAD"
		},
		"area_id": 18,
		"coalition_id": 6,
		"colors": [
			""
		],
		"fb_urls": [],
		"id": 25,
		"ig_urls": [],
		"logo_urls": [],
		"name": {
			"en_US": "FELICIDAD",
			"es_AR": "FELICIDAD"
		},
		"websites": []
	},
	{
		"abbreviation": {
			"en_US": "N/A",
			"es_AR": "FRENTE AMPLIO CATAMARQUEÑO"
		},
		"area_id": 3,
		"coalition_id": 6,
		"colors": [
			""
		],
		"fb_urls": [],
		"id": 26,
		"ig_urls": [],
		"logo_urls": [],
		"name": {
			"en_US": "FRENTE AMPLIO CATAMARQUEÑO",
			"es_AR": "FRENTE AMPLIO CATAMARQUEÑO"
		},
		"websites": []
	},
	{
		"abbreviation": {
			"en_US": "N/A",
			"es_AR": "FRENTE AMPLIO POR TUCUMAN"
		},
		"area_id": 25,
		"coalition_id": 6,
		"colors": [
			""
		],
		"fb_urls": [],
		"id": 27,
		"ig_urls": [],
		"logo_urls": [],
		"name": {
			"en_US": "FRENTE AMPLIO POR TUCUMAN",
			"es_AR": "FRENTE AMPLIO POR TUCUMAN"
		},
		"websites": []
	},
	{
		"abbreviation": {
			"en_US": "N/A",
			"es_AR": "FRENTE AMPLIO PROGRESISTA"
		},
		"area_id": 22,
		"coalition_id": 6,
		"colors": [
			""
		],
		"fb_urls": [],
		"id": 28,
		"ig_urls": [],
		"logo_urls": [],
		"name": {
			"en_US": "FRENTE AMPLIO PROGRESISTA",
			"es_AR": "FRENTE AMPLIO PROGRESISTA"
		},
		"websites": []
	},
	{
		"abbreviation": {
			"en_US": "N/A",
			"es_AR": "FRENTE CIVICO POR SANTIAGO"
		},
		"area_id": 23,
		"coalition_id": 6,
		"colors": [
			""
		],
		"fb_urls": [],
		"id": 29,
		"ig_urls": [],
		"logo_urls": [],
		"name": {
			"en_US": "FRENTE CIVICO POR SANTIAGO",
			"es_AR": "FRENTE CIVICO POR SANTIAGO"
		},
		"websites": []
	},
	{
		"abbreviation": {
			"en_US": "N/A",
			"es_AR": "FRENTE CONSENSO ISCHIGUALASTO (SAN JUAN)"
		},
		"area_id": 19,
		"coalition_id": 6,
		"colors": [
			""
		],
		"fb_urls": [],
		"id": 30,
		"ig_urls": [],
		"logo_urls": [],
		"name": {
			"en_US": "FRENTE CONSENSO ISCHIGUALASTO (SAN JUAN)",
			"es_AR": "FRENTE CONSENSO ISCHIGUALASTO (SAN JUAN)"
		},
		"websites": []
	},
	{
		"abbreviation": {
			"en_US": "FITU-T",
			"es_AR": "FRENTE DE IZQUIERDA Y DE LOS TRABAJADORES UNIDAD-TUC"
		},
		"area_id": 25,
		"coalition_id": 3,
		"colors": [
			""
		],
		"fb_urls": [],
		"id": 31,
		"ig_urls": [],
		"logo_urls": [],
		"name": {
			"en_US": "FRENTE DE IZQUIERDA Y DE LOS TRABAJADORES UNIDAD-TUC",
			"es_AR": "FRENTE DE IZQUIERDA Y DE LOS TRABAJADORES UNIDAD-TUC"
		},
		"websites": []
	},
	{
		"abbreviation": {
			"en_US": "FIT",
			"es_AR": "FRENTE DE IZQUIERDA Y DE TRABAJADORES"
		},
		"area_id": 2,
		"coalition_id": 3,
		"colors": [
			""
		],
		"fb_urls": [],
		"id": 32,
		"ig_urls": [],
		"logo_urls": [],
		"name": {
			"en_US": "FRENTE DE IZQUIERDA Y DE TRABAJADORES",
			"es_AR": "FRENTE DE IZQUIERDA Y DE TRABAJADORES"
		},
		"websites": []
	},
	{
		"abbreviation": {
			"en_US": "FITU",
			"es_AR": "FRENTE DE IZQUIERDA Y DE TRABAJADORES - UNIDAD"
		},
		"area_id": 1,
		"coalition_id": 3,
		"colors": [
			""
		],
		"fb_urls": [],
		"id": 33,
		"ig_urls": [],
		"logo_urls": [],
		"name": {
			"en_US": "FRENTE DE IZQUIERDA Y DE TRABAJADORES - UNIDAD",
			"es_AR": "FRENTE DE IZQUIERDA Y DE TRABAJADORES - UNIDAD"
		},
		"websites": []
	},
	{
		"abbreviation": {
			"en_US": "N/A",
			"es_AR": "FRENTE DE IZQUIERDA Y DE TRABAJADORES - UNIDAD - DISTRITO MENDOZA"
		},
		"area_id": 14,
		"coalition_id": 3,
		"colors": [
			""
		],
		"fb_urls": [],
		"id": 34,
		"ig_urls": [],
		"logo_urls": [],
		"name": {
			"en_US": "FRENTE DE IZQUIERDA Y DE TRABAJADORES - UNIDAD - DISTRITO MENDOZA",
			"es_AR": "FRENTE DE IZQUIERDA Y DE TRABAJADORES - UNIDAD - DISTRITO MENDOZA"
		},
		"websites": []
	},
	{
		"abbreviation": {
			"en_US": "N/A",
			"es_AR": "FRENTE DE IZQUIERDA Y DE TRABAJADORES - UNIDAD (SAN JUAN)"
		},
		"area_id": 19,
		"coalition_id": 3,
		"colors": [
			""
		],
		"fb_urls": [],
		"id": 35,
		"ig_urls": [],
		"logo_urls": [],
		"name": {
			"en_US": "FRENTE DE IZQUIERDA Y DE TRABAJADORES - UNIDAD (SAN JUAN)",
			"es_AR": "FRENTE DE IZQUIERDA Y DE TRABAJADORES - UNIDAD (SAN JUAN)"
		},
		"websites": []
	},
	{
		"abbreviation": {
			"en_US": "FDT",
			"es_AR": "FRENTE DE TODOS"
		},
		"area_id": 1,
		"coalition_id": 1,
		"colors": [
			""
		],
		"fb_urls": [],
		"id": 36,
		"ig_urls": [],
		"logo_urls": [],
		"name": {
			"en_US": "FRENTE DE TODOS",
			"es_AR": "FRENTE DE TODOS"
		},
		"websites": []
	},
	{
		"abbreviation": {
			"en_US": "N/A",
			"es_AR": "FRENTE DE TODOS - DISTRITO MENDOZA"
		},
		"area_id": 14,
		"coalition_id": 1,
		"colors": [
			""
		],
		"fb_urls": [],
		"id": 37,
		"ig_urls": [],
		"logo_urls": [],
		"name": {
			"en_US": "FRENTE DE TODOS - DISTRITO MENDOZA",
			"es_AR": "FRENTE DE TODOS - DISTRITO MENDOZA"
		},
		"websites": []
	},
	{
		"abbreviation": {
			"en_US": "N/A",
			"es_AR": "FRENTE DE TODOS (SAN JUAN)"
		},
		"area_id": 19,
		"coalition_id": 1,
		"colors": [
			""
		],
		"fb_urls": [],
		"id": 38,
		"ig_urls": [],
		"logo_urls": [],
		"name": {
			"en_US": "FRENTE DE TODOS (SAN JUAN)",
			"es_AR": "FRENTE DE TODOS (SAN JUAN)"
		},
		"websites": []
	},
	{
		"abbreviation": {
			"en_US": "N/A",
			"es_AR": "FRENTE DE TODOS (TUC)"
		},
		"area_id": 25,
		"coalition_id": 1,
		"colors": [
			""
		],
		"fb_urls": [],
		"id": 39,
		"ig_urls": [],
		"logo_urls": [],
		"name": {
			"en_US": "FRENTE DE TODOS (TUC)",
			"es_AR": "FRENTE DE TODOS (TUC)"
		},
		"websites": []
	},
	{
		"abbreviation": {
			"en_US": "FDT-PBA",
			"es_AR": "FRENTE DE TODOS PBA"
		},
		"area_id": 2,
		"coalition_id": 1,
		"colors": [
			""
		],
		"fb_urls": [],
		"id": 40,
		"ig_urls": [],
		"logo_urls": [],
		"name": {
			"en_US": "FRENTE DE TODOS PBA",
			"es_AR": "FRENTE DE TODOS PBA"
		},
		"websites": []
	},
	{
		"abbreviation": {
			"en_US": "N/A",
			"es_AR": "FRENTE JUNTOS POR EL CAMBIO"
		},
		"area_id": 15,
		"coalition_id": 2,
		"colors": [
			""
		],
		"fb_urls": [],
		"id": 41,
		"ig_urls": [],
		"logo_urls": [],
		"name": {
			"en_US": "FRENTE JUNTOS POR EL CAMBIO",
			"es_AR": "FRENTE JUNTOS POR EL CAMBIO"
		},
		"websites": []
	},
	{
		"abbreviation": {
			"en_US": "N/A",
			"es_AR": "FRENTE PATRIOTICO LABORISTA"
		},
		"area_id": 23,
		"coalition_id": 6,
		"colors": [
			""
		],
		"fb_urls": [],
		"id": 42,
		"ig_urls": [],
		"logo_urls": [],
		"name": {
			"en_US": "FRENTE PATRIOTICO LABORISTA",
			"es_AR": "FRENTE PATRIOTICO LABORISTA"
		},
		"websites": []
	},
	{
		"abbreviation": {
			"en_US": "FR",
			"es_AR": "FRENTE RENOVADOR"
		},
		"area_id": 23,
		"coalition_id": 1,
		"colors": [
			""
		],
		"fb_urls": [],
		"id": 43,
		"ig_urls": [],
		"logo_urls": [],
		"name": {
			"en_US": "FRENTE RENOVADOR",
			"es_AR": "FRENTE RENOVADOR"
		},
		"websites": []
	},
	{
		"abbreviation": {
			"en_US": "N/A",
			"es_AR": "FRENTE RENOVADOR DE LA CONCORDIA SOCIAL"
		},
		"area_id": 15,
		"coalition_id": 1,
		"colors": [
			""
		],
		"fb_urls": [],
		"id": 44,
		"ig_urls": [],
		"logo_urls": [],
		"name": {
			"en_US": "FRENTE RENOVADOR DE LA CONCORDIA SOCIAL",
			"es_AR": "FRENTE RENOVADOR DE LA CONCORDIA SOCIAL"
		},
		"websites": []
	},
	{
		"abbreviation": {
			"en_US": "N/A",
			"es_AR": "FRENTE SI + PRS"
		},
		"area_id": 18,
		"coalition_id": 6,
		"colors": [
			""
		],
		"fb_urls": [],
		"id": 45,
		"ig_urls": [],
		"logo_urls": [],
		"name": {
			"en_US": "FRENTE SI + PRS",
			"es_AR": "FRENTE SI + PRS"
		},
		"websites": []
	},
	{
		"abbreviation": {
			"en_US": "FDI",
			"es_AR": "FRENTEDEIZQUIERDA"
		},
		"area_id": 5,
		"coalition_id": 3,
		"colors": [
			""
		],
		"fb_urls": [],
		"id": 46,
		"ig_urls": [],
		"logo_urls": [],
		"name": {
			"en_US": "FRENTEDEIZQUIERDA",
			"es_AR": "FRENTEDEIZQUIERDA"
		},
		"websites": []
	},
	{
		"abbreviation": {
			"en_US": "N/A",
			"es_AR": "FUERZA REPUBLICANA TUC"
		},
		"area_id": 25,
		"coalition_id": 6,
		"colors": [
			""
		],
		"fb_urls": [],
		"id": 47,
		"ig_urls": [],
		"logo_urls": [],
		"name": {
			"en_US": "FUERZA REPUBLICANA TUC",
			"es_AR": "FUERZA REPUBLICANA TUC"
		},
		"websites": []
	},
	{
		"abbreviation": {
			"en_US": "N/A",
			"es_AR": "HACEMOS POR CORDOBA"
		},
		"area_id": 7,
		"coalition_id": 6,
		"colors": [
			""
		],
		"fb_urls": [],
		"id": 48,
		"ig_urls": [],
		"logo_urls": [],
		"name": {
			"en_US": "HACEMOS POR CORDOBA",
			"es_AR": "HACEMOS POR CORDOBA"
		},
		"websites": []
	},
	{
		"abbreviation": {
			"en_US": "JXC",
			"es_AR": "JUNTOS POR EL CAMBIO"
		},
		"area_id": 1,
		"coalition_id": 2,
		"colors": [
			""
		],
		"fb_urls": [],
		"id": 49,
		"ig_urls": [],
		"logo_urls": [],
		"name": {
			"en_US": "JUNTOS POR EL CAMBIO",
			"es_AR": "JUNTOS POR EL CAMBIO"
		},
		"websites": []
	},
	{
		"abbreviation": {
			"en_US": "N/A",
			"es_AR": "JUNTOS POR EL CAMBIO (SAN JUAN)"
		},
		"area_id": 19,
		"coalition_id": 2,
		"colors": [
			""
		],
		"fb_urls": [],
		"id": 50,
		"ig_urls": [],
		"logo_urls": [],
		"name": {
			"en_US": "JUNTOS POR EL CAMBIO (SAN JUAN)",
			"es_AR": "JUNTOS POR EL CAMBIO (SAN JUAN)"
		},
		"websites": []
	},
	{
		"abbreviation": {
			"en_US": "N/A",
			"es_AR": "JUNTOS POR EL CAMBIO +"
		},
		"area_id": 18,
		"coalition_id": 2,
		"colors": [
			""
		],
		"fb_urls": [],
		"id": 51,
		"ig_urls": [],
		"logo_urls": [],
		"name": {
			"en_US": "JUNTOS POR EL CAMBIO +",
			"es_AR": "JUNTOS POR EL CAMBIO +"
		},
		"websites": []
	},
	{
		"abbreviation": {
			"en_US": "N/A",
			"es_AR": "JUNTOS POR EL CAMBIO CHUBUT"
		},
		"area_id": 5,
		"coalition_id": 2,
		"colors": [
			""
		],
		"fb_urls": [],
		"id": 52,
		"ig_urls": [],
		"logo_urls": [],
		"name": {
			"en_US": "JUNTOS POR EL CAMBIO CHUBUT",
			"es_AR": "JUNTOS POR EL CAMBIO CHUBUT"
		},
		"websites": []
	},
	{
		"abbreviation": {
			"en_US": "N/A",
			"es_AR": "JUNTOS POR EL CAMBIO TIERRA DEL FUEGO"
		},
		"area_id": 24,
		"coalition_id": 2,
		"colors": [
			""
		],
		"fb_urls": [],
		"id": 53,
		"ig_urls": [],
		"logo_urls": [],
		"name": {
			"en_US": "JUNTOS POR EL CAMBIO TIERRA DEL FUEGO",
			"es_AR": "JUNTOS POR EL CAMBIO TIERRA DEL FUEGO"
		},
		"websites": []
	},
	{
		"abbreviation": {
			"en_US": "N/A",
			"es_AR": "JUNTOS POR EL CAMBIO TUCUMAN"
		},
		"area_id": 25,
		"coalition_id": 2,
		"colors": [
			""
		],
		"fb_urls": [],
		"id": 54,
		"ig_urls": [],
		"logo_urls": [],
		"name": {
			"en_US": "JUNTOS POR EL CAMBIO TUCUMAN",
			"es_AR": "JUNTOS POR EL CAMBIO TUCUMAN"
		},
		"websites": []
	},
	{
		"abbreviation": {
			"en_US": "N/A",
			"es_AR": "JUNTOS POR ENTRE RIOS"
		},
		"area_id": 9,
		"coalition_id": 2,
		"colors": [
			""
		],
		"fb_urls": [],
		"id": 55,
		"ig_urls": [],
		"logo_urls": [],
		"name": {
			"en_US": "JUNTOS POR ENTRE RIOS",
			"es_AR": "JUNTOS POR ENTRE RIOS"
		},
		"websites": []
	},
	{
		"abbreviation": {
			"en_US": "N/A",
			"es_AR": "JUNTOS POR FORMOSA LIBRE"
		},
		"area_id": 10,
		"coalition_id": 2,
		"colors": [
			""
		],
		"fb_urls": [],
		"id": 56,
		"ig_urls": [],
		"logo_urls": [],
		"name": {
			"en_US": "JUNTOS POR FORMOSA LIBRE",
			"es_AR": "JUNTOS POR FORMOSA LIBRE"
		},
		"websites": []
	},
	{
		"abbreviation": {
			"en_US": "N/A",
			"es_AR": "JUNTOS SOMOS RIO NEGRO"
		},
		"area_id": 17,
		"coalition_id": 2,
		"colors": [
			""
		],
		"fb_urls": [],
		"id": 57,
		"ig_urls": [],
		"logo_urls": [],
		"name": {
			"en_US": "JUNTOS SOMOS RIO NEGRO",
			"es_AR": "JUNTOS SOMOS RIO NEGRO"
		},
		"websites": []
	},
	{
		"abbreviation": {
			"en_US": "LLA",
			"es_AR": "LA LIBERTAD AVANZA"
		},
		"area_id": 7,
		"coalition_id": 5,
		"colors": [
			""
		],
		"fb_urls": [],
		"id": 58,
		"ig_urls": [],
		"logo_urls": [],
		"name": {
			"en_US": "LA LIBERTAD AVANZA",
			"es_AR": "LA LIBERTAD AVANZA"
		},
		"websites": []
	},
	{
		"abbreviation": {
			"en_US": "N/A",
			"es_AR": "LIBERTAD VALORES Y CAMBIO"
		},
		"area_id": 15,
		"coalition_id": 5,
		"colors": [
			""
		],
		"fb_urls": [],
		"id": 59,
		"ig_urls": [],
		"logo_urls": [],
		"name": {
			"en_US": "LIBERTAD VALORES Y CAMBIO",
			"es_AR": "LIBERTAD VALORES Y CAMBIO"
		},
		"websites": []
	},
	{
		"abbreviation": {
			"en_US": "N/A",
			"es_AR": "MOVIMIENTO AL SOCIALISMO"
		},
		"area_id": 1,
		"coalition_id": 3,
		"colors": [
			""
		],
		"fb_urls": [],
		"id": 60,
		"ig_urls": [],
		"logo_urls": [],
		"name": {
			"en_US": "MOVIMIENTO AL SOCIALISMO",
			"es_AR": "MOVIMIENTO AL SOCIALISMO"
		},
		"websites": []
	},
	{
		"abbreviation": {
			"en_US": "MLS",
			"es_AR": "MOVIMIENTO LIBRES DEL SUR"
		},
		"area_id": 1,
		"coalition_id": 1,
		"colors": [
			""
		],
		"fb_urls": [],
		"id": 61,
		"ig_urls": [],
		"logo_urls": [],
		"name": {
			"en_US": "MOVIMIENTO LIBRES DEL SUR",
			"es_AR": "MOVIMIENTO LIBRES DEL SUR"
		},
		"websites": []
	},
	{
		"abbreviation": {
			"en_US": "MPF",
			"es_AR": "MOVIMIENTO POPULAR FUEGUINO"
		},
		"area_id": 24,
		"coalition_id": 6,
		"colors": [
			""
		],
		"fb_urls": [],
		"id": 62,
		"ig_urls": [],
		"logo_urls": [],
		"name": {
			"en_US": "MOVIMIENTO POPULAR FUEGUINO",
			"es_AR": "MOVIMIENTO POPULAR FUEGUINO"
		},
		"websites": []
	},
	{
		"abbreviation": {
			"en_US": "MPN",
			"es_AR": "MOVIMIENTO POPULAR NEUQUINO"
		},
		"area_id": 16,
		"coalition_id": 6,
		"colors": [
			""
		],
		"fb_urls": [],
		"id": 63,
		"ig_urls": [],
		"logo_urls": [],
		"name": {
			"en_US": "MOVIMIENTO POPULAR NEUQUINO",
			"es_AR": "MOVIMIENTO POPULAR NEUQUINO"
		},
		"websites": []
	},
	{
		"abbreviation": {
			"en_US": "NI",
			"es_AR": "NUEVA IZQUIERDA"
		},
		"area_id": 9,
		"coalition_id": 3,
		"colors": [
			""
		],
		"fb_urls": [],
		"id": 64,
		"ig_urls": [],
		"logo_urls": [],
		"name": {
			"en_US": "NUEVA IZQUIERDA",
			"es_AR": "NUEVA IZQUIERDA"
		},
		"websites": []
	},
	{
		"abbreviation": {
			"en_US": "N/A",
			"es_AR": "PARTIDO CONSERVADOR POPULAR"
		},
		"area_id": 9,
		"coalition_id": 6,
		"colors": [
			""
		],
		"fb_urls": [],
		"id": 65,
		"ig_urls": [],
		"logo_urls": [],
		"name": {
			"en_US": "PARTIDO CONSERVADOR POPULAR",
			"es_AR": "PARTIDO CONSERVADOR POPULAR"
		},
		"websites": []
	},
	{
		"abbreviation": {
			"en_US": "PDO",
			"es_AR": "PARTIDO DEL OBRERO"
		},
		"area_id": 4,
		"coalition_id": 3,
		"colors": [
			""
		],
		"fb_urls": [],
		"id": 66,
		"ig_urls": [],
		"logo_urls": [],
		"name": {
			"en_US": "PARTIDO DEL OBRERO",
			"es_AR": "PARTIDO DEL OBRERO"
		},
		"websites": []
	},
	{
		"abbreviation": {
			"en_US": "N/A",
			"es_AR": "PARTIDO FE"
		},
		"area_id": 9,
		"coalition_id": 6,
		"colors": [
			""
		],
		"fb_urls": [],
		"id": 67,
		"ig_urls": [],
		"logo_urls": [],
		"name": {
			"en_US": "PARTIDO FE",
			"es_AR": "PARTIDO FE"
		},
		"websites": []
	},
	{
		"abbreviation": {
			"en_US": "N/A",
			"es_AR": "PARTIDO FEDERAL - DISTRITO MENDOZA"
		},
		"area_id": 14,
		"coalition_id": 6,
		"colors": [
			""
		],
		"fb_urls": [],
		"id": 68,
		"ig_urls": [],
		"logo_urls": [],
		"name": {
			"en_US": "PARTIDO FEDERAL - DISTRITO MENDOZA",
			"es_AR": "PARTIDO FEDERAL - DISTRITO MENDOZA"
		},
		"websites": []
	},
	{
		"abbreviation": {
			"en_US": "N/A",
			"es_AR": "PARTIDO FRENTE INTEGRADOR"
		},
		"area_id": 4,
		"coalition_id": 6,
		"colors": [
			""
		],
		"fb_urls": [],
		"id": 69,
		"ig_urls": [],
		"logo_urls": [],
		"name": {
			"en_US": "PARTIDO FRENTE INTEGRADOR",
			"es_AR": "PARTIDO FRENTE INTEGRADOR"
		},
		"websites": []
	},
	{
		"abbreviation": {
			"en_US": "N/A",
			"es_AR": "PARTIDO INDEPENDIENTE DEL CHUBUT"
		},
		"area_id": 5,
		"coalition_id": 6,
		"colors": [
			""
		],
		"fb_urls": [],
		"id": 70,
		"ig_urls": [],
		"logo_urls": [],
		"name": {
			"en_US": "PARTIDO INDEPENDIENTE DEL CHUBUT",
			"es_AR": "PARTIDO INDEPENDIENTE DEL CHUBUT"
		},
		"websites": []
	},
	{
		"abbreviation": {
			"en_US": "PO",
			"es_AR": "PARTIDO OBRERO"
		},
		"area_id": 24,
		"coalition_id": 3,
		"colors": [
			""
		],
		"fb_urls": [],
		"id": 71,
		"ig_urls": [],
		"logo_urls": [],
		"name": {
			"en_US": "PARTIDO OBRERO",
			"es_AR": "PARTIDO OBRERO"
		},
		"websites": []
	},
	{
		"abbreviation": {
			"en_US": "N/A",
			"es_AR": "PARTIDO POR UN SANTIAGO OBRERO"
		},
		"area_id": 23,
		"coalition_id": 3,
		"colors": [
			""
		],
		"fb_urls": [],
		"id": 72,
		"ig_urls": [],
		"logo_urls": [],
		"name": {
			"en_US": "PARTIDO POR UN SANTIAGO OBRERO",
			"es_AR": "PARTIDO POR UN SANTIAGO OBRERO"
		},
		"websites": []
	},
	{
		"abbreviation": {
			"en_US": "N/A",
			"es_AR": "PARTIDO PRINCIPIOS Y CONVICCION"
		},
		"area_id": 10,
		"coalition_id": 6,
		"colors": [
			""
		],
		"fb_urls": [],
		"id": 73,
		"ig_urls": [],
		"logo_urls": [],
		"name": {
			"en_US": "PARTIDO PRINCIPIOS Y CONVICCION",
			"es_AR": "PARTIDO PRINCIPIOS Y CONVICCION"
		},
		"websites": []
	},
	{
		"abbreviation": {
			"en_US": "P.S",
			"es_AR": "PARTIDO SOCIALISTA"
		},
		"area_id": 1,
		"coalition_id": 2,
		"colors": [
			""
		],
		"fb_urls": [],
		"id": 74,
		"ig_urls": [],
		"logo_urls": [],
		"name": {
			"en_US": "PARTIDO SOCIALISTA",
			"es_AR": "PARTIDO SOCIALISTA"
		},
		"websites": []
	},
	{
		"abbreviation": {
			"en_US": "N/A",
			"es_AR": "PARTIDO VERDE - DISTRITO MENDOZA"
		},
		"area_id": 14,
		"coalition_id": 6,
		"colors": [
			""
		],
		"fb_urls": [],
		"id": 75,
		"ig_urls": [],
		"logo_urls": [],
		"name": {
			"en_US": "PARTIDO VERDE - DISTRITO MENDOZA",
			"es_AR": "PARTIDO VERDE - DISTRITO MENDOZA"
		},
		"websites": []
	},
	{
		"abbreviation": {
			"en_US": "N/A",
			"es_AR": "PODEMOS"
		},
		"area_id": 22,
		"coalition_id": 6,
		"colors": [
			""
		],
		"fb_urls": [],
		"id": 76,
		"ig_urls": [],
		"logo_urls": [],
		"name": {
			"en_US": "PODEMOS",
			"es_AR": "PODEMOS"
		},
		"websites": []
	},
	{
		"abbreviation": {
			"en_US": "N/A",
			"es_AR": "POLITICAOBRERA"
		},
		"area_id": 18,
		"coalition_id": 3,
		"colors": [
			""
		],
		"fb_urls": [],
		"id": 77,
		"ig_urls": [],
		"logo_urls": [],
		"name": {
			"en_US": "POLITICAOBRERA",
			"es_AR": "POLITICAOBRERA"
		},
		"websites": []
	},
	{
		"abbreviation": {
			"en_US": "N/A",
			"es_AR": "PRIMERO SANTA FE"
		},
		"area_id": 22,
		"coalition_id": 6,
		"colors": [
			""
		],
		"fb_urls": [],
		"id": 78,
		"ig_urls": [],
		"logo_urls": [],
		"name": {
			"en_US": "PRIMERO SANTA FE",
			"es_AR": "PRIMERO SANTA FE"
		},
		"websites": []
	},
	{
		"abbreviation": {
			"en_US": "N/A",
			"es_AR": "REPUBLICANOS UNIDOS"
		},
		"area_id": 24,
		"coalition_id": 6,
		"colors": [
			""
		],
		"fb_urls": [],
		"id": 79,
		"ig_urls": [],
		"logo_urls": [],
		"name": {
			"en_US": "REPUBLICANOS UNIDOS",
			"es_AR": "REPUBLICANOS UNIDOS"
		},
		"websites": []
	},
	{
		"abbreviation": {
			"en_US": "N/A",
			"es_AR": "SOMOS ENERGIA PARA RENOVAR SANTA CRUZ - SER"
		},
		"area_id": 21,
		"coalition_id": 6,
		"colors": [
			""
		],
		"fb_urls": [],
		"id": 80,
		"ig_urls": [],
		"logo_urls": [],
		"name": {
			"en_US": "SOMOS ENERGIA PARA RENOVAR SANTA CRUZ - SER",
			"es_AR": "SOMOS ENERGIA PARA RENOVAR SANTA CRUZ - SER"
		},
		"websites": []
	},
	{
		"abbreviation": {
			"en_US": "N/A",
			"es_AR": "SOMOS FUEGUINOS"
		},
		"area_id": 24,
		"coalition_id": 6,
		"colors": [
			""
		],
		"fb_urls": [],
		"id": 81,
		"ig_urls": [],
		"logo_urls": [],
		"name": {
			"en_US": "SOMOS FUEGUINOS",
			"es_AR": "SOMOS FUEGUINOS"
		},
		"websites": []
	},
	{
		"abbreviation": {
			"en_US": "N/A",
			"es_AR": "SOMOS FUTURO"
		},
		"area_id": 22,
		"coalition_id": 6,
		"colors": [
			""
		],
		"fb_urls": [],
		"id": 82,
		"ig_urls": [],
		"logo_urls": [],
		"name": {
			"en_US": "SOMOS FUTURO",
			"es_AR": "SOMOS FUTURO"
		},
		"websites": []
	},
	{
		"abbreviation": {
			"en_US": "N/A",
			"es_AR": "TODOS UNIDOS SAN LUIS"
		},
		"area_id": 20,
		"coalition_id": 6,
		"colors": [
			""
		],
		"fb_urls": [],
		"id": 83,
		"ig_urls": [],
		"logo_urls": [],
		"name": {
			"en_US": "TODOS UNIDOS SAN LUIS",
			"es_AR": "TODOS UNIDOS SAN LUIS"
		},
		"websites": []
	},
	{
		"abbreviation": {
			"en_US": "N/A",
			"es_AR": "UNIDOS POR SALTA"
		},
		"area_id": 18,
		"coalition_id": 6,
		"colors": [
			""
		],
		"fb_urls": [],
		"id": 84,
		"ig_urls": [],
		"logo_urls": [],
		"name": {
			"en_US": "UNIDOS POR SALTA",
			"es_AR": "UNIDOS POR SALTA"
		},
		"websites": []
	},
	{
		"abbreviation": {
			"en_US": "UCR",
			"es_AR": "UNION CIVICA RADICAL SAN LUIS"
		},
		"area_id": 20,
		"coalition_id": 2,
		"colors": [
			""
		],
		"fb_urls": [],
		"id": 85,
		"ig_urls": [],
		"logo_urls": [],
		"name": {
			"en_US": "UNION CIVICA RADICAL SAN LUIS",
			"es_AR": "UNION CIVICA RADICAL SAN LUIS"
		},
		"websites": []
	},
	{
		"abbreviation": {
			"en_US": "N/A",
			"es_AR": "UNION POPULAR FEDERAL"
		},
		"area_id": 7,
		"coalition_id": 6,
		"colors": [
			""
		],
		"fb_urls": [],
		"id": 86,
		"ig_urls": [],
		"logo_urls": [],
		"name": {
			"en_US": "UNION POPULAR FEDERAL",
			"es_AR": "UNION POPULAR FEDERAL"
		},
		"websites": []
	},
	{
		"abbreviation": {
			"en_US": "N/A",
			"es_AR": "UNITE POR LA LIBERTAD Y LA DIGNIDAD"
		},
		"area_id": 1,
		"coalition_id": 6,
		"colors": [
			""
		],
		"fb_urls": [],
		"id": 87,
		"ig_urls": [],
		"logo_urls": [],
		"name": {
			"en_US": "UNITE POR LA LIBERTAD Y LA DIGNIDAD",
			"es_AR": "UNITE POR LA LIBERTAD Y LA DIGNIDAD"
		},
		"websites": []
	},
	{
		"abbreviation": {
			"en_US": "N/A",
			"es_AR": "VAMOS! MENDOCINOS - DISTRITO MENDOZA"
		},
		"area_id": 14,
		"coalition_id": 6,
		"colors": [
			""
		],
		"fb_urls": [],
		"id": 88,
		"ig_urls": [],
		"logo_urls": [],
		"name": {
			"en_US": "VAMOS! MENDOCINOS - DISTRITO MENDOZA",
			"es_AR": "VAMOS! MENDOCINOS - DISTRITO MENDOZA"
		},
		"websites": []
	},
	{
		"abbreviation": {
			"en_US": "UCEDE",
			"es_AR": "UCEDE - UNION DEL CENTRO DEMOCRATICO"
		},
		"area_id": 13,
		"coalition_id": 6,
		"colors": [
			""
		],
		"fb_urls": [],
		"id": 89,
		"ig_urls": [],
		"logo_urls": [],
		"name": {
			"en_US": "UCEDE - UNION DEL CENTRO DEMOCRATICO",
			"es_AR": "UCEDE - UNION DEL CENTRO DEMOCRATICO"
		},
		"websites": []
	},
	{
		"abbreviation": {
			"en_US": "N/A",
			"es_AR": "UNIDOS"
		},
		"area_id": 13,
		"coalition_id": 6,
		"colors": [
			""
		],
		"fb_urls": [],
		"id": 90,
		"ig_urls": [],
		"logo_urls": [],
		"name": {
			"en_US": "UNIDOS",
			"es_AR": "UNIDOS"
		},
		"websites": []
	},
	{
		"abbreviation": {
			"en_US": "N/A",
			"es_AR": "VAMOS LA RIOJA - CAMBIA LA RIOJA"
		},
		"area_id": 13,
		"coalition_id": 6,
		"colors": [
			""
		],
		"fb_urls": [],
		"id": 91,
		"ig_urls": [],
		"logo_urls": [],
		"name": {
			"en_US": "VAMOS LA RIOJA - CAMBIA LA RIOJA",
			"es_AR": "VAMOS LA RIOJA - CAMBIA LA RIOJA"
		},
		"websites": []
	},
	{
		"abbreviation": {
			"en_US": "N/A",
			"es_AR": "SOBERANIA POPULAR (1)"
		},
		"area_id": 22,
		"coalition_id": 6,
		"colors": [
			""
		],
		"fb_urls": [],
		"id": 92,
		"ig_urls": [],
		"logo_urls": [],
		"name": {
			"en_US": "SOBERANIA POPULAR (1)",
			"es_AR": "SOBERANIA POPULAR (1)"
		},
		"websites": []
	}
]